LICENSE
MANIFEST.in
README.rst
requirements.txt
setup.cfg
setup.py
knot_injector/__init__.py
knot_injector.egg-info/PKG-INFO
knot_injector.egg-info/SOURCES.txt
knot_injector.egg-info/dependency_links.txt
knot_injector.egg-info/not-zip-safe
knot_injector.egg-info/requires.txt
knot_injector.egg-info/top_level.txt