Metadata-Version: 1.1
Name: knot-injector
Version: 0.0.3
Summary: Framework agnostic dependency injections
Home-page: https://github.com/rdidyk/knot-injector
Author: Ruslan Didyk
Author-email: rdidyk@tmgtop.com
License: MIT
Download-URL: https://github.com/rdidyk/knot-injector/archive/0.0.3.tar.gz
Keywords: dependencies injection
Platform: UNKNOWN
Classifier: Intended Audience :: Developers
Classifier: License :: OSI Approved :: MIT License
Classifier: Programming Language :: Python :: 3
Classifier: Programming Language :: Python :: 3.4
Classifier: Programming Language :: Python :: 3.5
